Metadata-Version: 1.0
Name: servo-tidy
Version: 0.3.0
Summary: The servo-tidy is used to check licenses, line lengths, whitespace, flake8 on Python files, lock file versions, and more.
Home-page: https://github.com/servo/servo
Author: The Servo Project Developers
Author-email: dev-servo@lists.mozilla.org
License: UNKNOWN
Keywords: mozilla servo tidy
Platform: UNKNOWN
